process_inspector/__init__.py
process_inspector/taskcontrol.py
process_inspector/appcontrol/__init__.py
process_inspector/appcontrol/interface.py
process_inspector/appcontrol/linux.py
process_inspector/appcontrol/mac.py
process_inspector/appcontrol/windows.py
process_inspector/oscontrol/__init__.py
process_inspector/oscontrol/interface.py
process_inspector/oscontrol/linux.py
process_inspector/oscontrol/mac.py
process_inspector/oscontrol/windows.py
process_inspector/servicecontrol/__init__.py
process_inspector/servicecontrol/interface.py
process_inspector/servicecontrol/linux.py
process_inspector/servicecontrol/mac.py
process_inspector/servicecontrol/windows.py
process_inspector/servicecontrol/implementations/__init__.py
process_inspector/servicecontrol/implementations/supervisorctl.py
process_inspector/servicecontrol/implementations/systemctl.py
process_inspector/teamviewer/__init__.py
process_inspector/teamviewer/linux.py
process_inspector/teamviewer/mac.py
process_inspector/teamviewer/teamviewer.py
process_inspector/teamviewer/windows.py
process_inspector/unity/__init__.py
process_inspector/unity/base.py
process_inspector/unity/linux.py
process_inspector/unity/mac.py
process_inspector/unity/windows.py
process_inspector/utils/__init__.py
process_inspector/utils/byteutils.py
process_inspector/utils/datetimeutils.py
process_inspector/utils/importutils.py
process_inspector/utils/processutils.py
process_inspector/utils/stringutils.py
process_inspector-0.2.0.dist-info/licenses/AUTHORS.md
process_inspector-0.2.0.dist-info/licenses/LICENSE
process_inspector-0.2.0.dist-info/METADATA
process_inspector-0.2.0.dist-info/WHEEL
process_inspector-0.2.0.dist-info/top_level.txt
process_inspector-0.2.0.dist-info/RECORD
