Metadata-Version: 2.4
Name: process-inspector
Version: 0.2.0
Summary: A Python package for cross-platform process management, providing process data as dicts/JSON and allowing process control (start, stop, kill) on Windows, Mac, and Linux.
Author-email: Tim Santor <tsantor@xstudios.com>
Project-URL: Repository, https://bitbucket.org/xstudios/process-inspector.git
Project-URL: Issues, https://bitbucket.org/xstudios/process-inspector/issues
Project-URL: Changelog, https://bitbucket.org/xstudios/process-inspector/blob/master/HISTORY.md
Classifier: Development Status :: 5 - Production/Stable
Classifier: Environment :: Console
Classifier: Intended Audience :: Developers
Classifier: Natural Language :: English
Classifier: Programming Language :: Python :: 3.11
Classifier: Programming Language :: Python :: 3.12
Classifier: Programming Language :: Python :: 3.13
Requires-Python: >=3.11
License-File: LICENSE
License-File: AUTHORS.md
Requires-Dist: humanize>=4.14.0
Requires-Dist: psutil>=7.1.3
Dynamic: license-file
